ipaddons/__init__.py
ipaddons/_version.py
ipaddons/py.typed
ipaddons/tools.py
ipaddons-0.4.0.dist-info/METADATA
ipaddons-0.4.0.dist-info/WHEEL
ipaddons-0.4.0.dist-info/licenses/LICENSE
ipaddons-0.4.0.dist-info/RECORD
