Metadata-Version: 2.4
Name: ipaddons
Version: 0.4.0
Summary: Additional tools for the ipaddress standard library module
Project-URL: documentation, https://ipaddons.readthedocs.io/
Project-URL: homepage, https://gitlab.com/sebastianw/ipaddons/
Project-URL: repository, https://gitlab.com/sebastianw/ipaddons/
Author-email: Sebastian Wiesinger <sebastian@karotte.org>
License-Expression: MIT
License-File: LICENSE
Classifier: Development Status :: 3 - Alpha
Classifier: Operating System :: OS Independent
Classifier: Programming Language :: Python :: 3 :: Only
Classifier: Programming Language :: Python :: 3.11
Classifier: Programming Language :: Python :: 3.12
Classifier: Programming Language :: Python :: 3.13
Classifier: Programming Language :: Python :: 3.14
Classifier: Topic :: Utilities
Requires-Python: >=3.11
